odoo8_addon_account_banking_payment_transfer-8.0.0.3.1-py2.7-nspkg.pth
odoo_addons/account_banking_payment_transfer/post_install.py
odoo_addons/account_banking_payment_transfer/__openerp__.py
odoo_addons/account_banking_payment_transfer/__init__.py
odoo_addons/account_banking_payment_transfer/README.rst
odoo_addons/account_banking_payment_transfer/view/account_payment.xml
odoo_addons/account_banking_payment_transfer/view/payment_mode.xml
odoo_addons/account_banking_payment_transfer/i18n/it.po
odoo_addons/account_banking_payment_transfer/i18n/es.po
odoo_addons/account_banking_payment_transfer/i18n/sl.po
odoo_addons/account_banking_payment_transfer/i18n/account_banking_payment.pot
odoo_addons/account_banking_payment_transfer/i18n/nl.po
odoo_addons/account_banking_payment_transfer/i18n/de.po
odoo_addons/account_banking_payment_transfer/i18n/fr.po
odoo_addons/account_banking_payment_transfer/i18n/pt_BR.po
odoo_addons/account_banking_payment_transfer/model/payment_mode.py
odoo_addons/account_banking_payment_transfer/model/__init__.py
odoo_addons/account_banking_payment_transfer/model/account_payment.py
odoo_addons/account_banking_payment_transfer/model/account_move_reconcile.py
odoo_addons/account_banking_payment_transfer/model/payment_line.py
odoo_addons/account_banking_payment_transfer/model/bank_payment_line.py
odoo_addons/account_banking_payment_transfer/test/test_partial_payment_refunded.yml
odoo_addons/account_banking_payment_transfer/test/test_partial_payment_transfer.yml
odoo_addons/account_banking_payment_transfer/test/data.yml
odoo_addons/account_banking_payment_transfer/test/test_payment_method.yml
odoo_addons/account_banking_payment_transfer/workflow/account_payment.xml
odoo_addons/account_banking_payment_transfer/static/description/icon.png
odoo8_addon_account_banking_payment_transfer-8.0.0.3.1.dist-info/top_level.txt
odoo8_addon_account_banking_payment_transfer-8.0.0.3.1.dist-info/WHEEL
odoo8_addon_account_banking_payment_transfer-8.0.0.3.1.dist-info/RECORD
odoo8_addon_account_banking_payment_transfer-8.0.0.3.1.dist-info/metadata.json
odoo8_addon_account_banking_payment_transfer-8.0.0.3.1.dist-info/DESCRIPTION.rst
odoo8_addon_account_banking_payment_transfer-8.0.0.3.1.dist-info/METADATA
odoo8_addon_account_banking_payment_transfer-8.0.0.3.1.dist-info/namespace_packages.txt
