Metadata-Version: 2.0
Name: odoo8-addon-account-banking-payment-transfer
Version: 8.0.0.3.1
Summary: Account Banking - Payments Transfer Account
Home-page: https://github.com/OCA/banking
Author: UNKNOWN
Author-email: UNKNOWN
License: AGPL-3
Platform: UNKNOWN
Requires-Dist: odoo (<9.0a,>=8.0a)
Requires-Dist: odoo8-addon-account-banking-payment-export
Classifier: Programming Language :: Python :: 2.7
Classifier: Framework :: Odoo
Classifier: License :: OSI Approved :: GNU Affero General Public License v3
